rainbow_logging/__init__.py
rainbow_logging/rainbow_logger.py
rainbow_logging/timezone.py
rainbow_logging-0.0.1.dist-info/licenses/LICENSE
rainbow_logging-0.0.1.dist-info/METADATA
rainbow_logging-0.0.1.dist-info/WHEEL
rainbow_logging-0.0.1.dist-info/top_level.txt
rainbow_logging-0.0.1.dist-info/RECORD
