Metadata-Version: 2.4
Name: rainbow_logging
Version: 0.0.1
Summary: 🌈 A flexible and minimal Python logging utility that adds colorful, readable log output to your terminal.
Author-email: spring <springnode@gmail.com>
License: MIT
Project-URL: Homepage, https://github.com/NLPOptimize/rainbow_logging
Project-URL: Issues, https://github.com/NLPOptimize/rainbow_logging/issues
Keywords: python,logging,color
Classifier: Development Status :: 2 - Pre-Alpha
Classifier: Programming Language :: Python :: 3
Classifier: Operating System :: OS Independent
Requires-Python: >=3.7
License-File: LICENSE
Requires-Dist: pytz
Dynamic: license-file
